movieback.py
movieback-0.1.1.dist-info/METADATA
movieback-0.1.1.dist-info/WHEEL
movieback-0.1.1.dist-info/RECORD
