Metadata-Version: 2.1
Name: movieback
Version: 0.1.1
Summary: 
Home-page: https://codeberg.org/Tuxilio/movieback
License: LICENSE
Author: Tuxilio
Author-email: mail@tuxil.io
Requires-Python: >=3.8,<4.0
Classifier: License :: Other/Proprietary License
Classifier: Programming Language :: Python :: 3
Classifier: Programming Language :: Python :: 3.8
Classifier: Programming Language :: Python :: 3.9
Classifier: Programming Language :: Python :: 3.10
Classifier: Programming Language :: Python :: 3.11
Classifier: Programming Language :: Python :: 3.12
Project-URL: Repository, https://codeberg.org/Tuxilio/movieback
